LICENSE.txt
click_rich_help/__init__.py
click_rich_help/core.py
click_rich_help/decorators.py
click_rich_help/example.py
click_rich_help/py.typed
click_rich_help/utils.py
click_rich_help-22.1.1.dist-info/LICENSE.txt
click_rich_help-22.1.1.dist-info/WHEEL
click_rich_help-22.1.1.dist-info/METADATA
click_rich_help-22.1.1.dist-info/RECORD
