Metadata-Version: 2.1
Name: click-rich-help
Version: 22.1.1
Summary: make a beautiful click app with rich
Home-page: https://github.com/daylinmorgan/click-rich-help
License: MIT
Author: Daylin Morgan
Author-email: daylinmorgan@gmail.com
Requires-Python: >=3.7,<4.0
Classifier: License :: OSI Approved :: MIT License
Classifier: Programming Language :: Python :: 3
Classifier: Programming Language :: Python :: 3.10
Classifier: Programming Language :: Python :: 3.7
Classifier: Programming Language :: Python :: 3.8
Classifier: Programming Language :: Python :: 3.9
Requires-Dist: click (>=8.0,<9.0)
Requires-Dist: rich (>=10.0)
Project-URL: Repository, https://github.com/daylinmorgan/click-rich-help
